qdrant_mcp/__init__.py
qdrant_mcp/qdrant_memory.py
qdrant_mcp/server.py
qdrant_mcp/settings.py
qdrant_mcp/embeddings/__init__.py
qdrant_mcp/embeddings/base.py
qdrant_mcp/embeddings/factory.py
qdrant_mcp/embeddings/openai.py
qdrant_mcp/embeddings/sentence_transformers.py
qdrant_mcp-0.2.0.dist-info/METADATA
qdrant_mcp-0.2.0.dist-info/WHEEL
qdrant_mcp-0.2.0.dist-info/entry_points.txt
qdrant_mcp-0.2.0.dist-info/licenses/LICENSE
qdrant_mcp-0.2.0.dist-info/RECORD
