Metadata-Version: 2.4
Name: qdrant-mcp
Version: 0.2.0
Summary: Qdrant MCP server with configurable embedding providers
Project-URL: Homepage, https://github.com/andrewlwn77/qdrant-mcp
Project-URL: Repository, https://github.com/andrewlwn77/qdrant-mcp
Project-URL: Issues, https://github.com/andrewlwn77/qdrant-mcp/issues
Author-email: Andrew Lewin <andrew@example.com>
License: Apache-2.0
License-File: LICENSE
Keywords: embeddings,mcp,qdrant,semantic-search,vector-search
Classifier: Development Status :: 4 - Beta
Classifier: Intended Audience :: Developers
Classifier: License :: OSI Approved :: Apache Software License
Classifier: Programming Language :: Python :: 3
Classifier: Programming Language :: Python :: 3.10
Classifier: Programming Language :: Python :: 3.11
Classifier: Programming Language :: Python :: 3.12
Classifier: Topic :: Scientific/Engineering :: Artificial Intelligence
Classifier: Topic :: Software Development :: Libraries :: Python Modules
Requires-Python: >=3.10
Requires-Dist: httpx>=0.27.2
Requires-Dist: mcp[cli]>=1.2.0
Requires-Dist: numpy>=1.26.0
Requires-Dist: openai>=1.55.0
Requires-Dist: pydantic-settings>=2.6.0
Requires-Dist: pydantic>=2.9.2
Requires-Dist: qdrant-client>=1.11.0
Provides-Extra: dev
Requires-Dist: mypy>=1.11.0; extra == 'dev'
Requires-Dist: pytest-asyncio>=0.24.0; extra == 'dev'
Requires-Dist: pytest>=8.3.0; extra == 'dev'
Requires-Dist: ruff>=0.7.0; extra == 'dev'
